zptess/__init__.py
zptess/_version.py
zptess/constants.py
zptess/dao.py
zptess/cli/__init__.py
zptess/cli/batch.py
zptess/cli/calibrate.py
zptess/cli/reader.py
zptess/cli/tools.py
zptess/cli/writer.py
zptess/cli/util/__init__.py
zptess/cli/util/misc.py
zptess/cli/util/parser.py
zptess/cli/util/validator.py
zptess/controller/__init__.py
zptess/controller/exporter.py
zptess/controller/batch/__init__.py
zptess/controller/batch/batch.py
zptess/controller/photometer/__init__.py
zptess/controller/photometer/base.py
zptess/controller/photometer/builder.py
zptess/controller/photometer/persistent.py
zptess/controller/photometer/reader.py
zptess/controller/photometer/ring.py
zptess/controller/photometer/types.py
zptess/controller/photometer/util.py
zptess/controller/photometer/volatile.py
zptess/controller/photometer/writer.py
zptess-6.2.4.data/scripts/zp-db-fix-src
zptess-6.2.4.dist-info/licenses/LICENSE
zptess-6.2.4.dist-info/METADATA
zptess-6.2.4.dist-info/WHEEL
zptess-6.2.4.dist-info/entry_points.txt
zptess-6.2.4.dist-info/top_level.txt
zptess-6.2.4.dist-info/RECORD
