Metadata-Version: 2.4
Name: zptess
Version: 6.2.4
Summary: TESS-W Calibration tool
Author-email: Rafael González <rafael08@ucm.es>
Project-URL: Homepage, https://github.com/astrorafael/textual-zptess
Project-URL: Repository, https://github.com/astrorafael/textual-zptess.git
Classifier: Programming Language :: Python :: 3.12
Classifier: Programming Language :: Python :: 3.13
Classifier: Development Status :: 3 - Alpha
Classifier: Environment :: Console
Classifier: Intended Audience :: Science/Research
Classifier: Operating System :: POSIX :: Linux
Classifier: Topic :: Scientific/Engineering :: Astronomy
Classifier: Topic :: Scientific/Engineering :: Atmospheric Science
Requires-Python: >=3.12
License-File: LICENSE
Requires-Dist: python-decouple>=3.8
Requires-Dist: typing-extensions>=4.12
Requires-Dist: zptess-dao>=1.0
Requires-Dist: pypubsub>=4.0
Requires-Dist: lica[photometer,tabular]>=3.0
Dynamic: license-file
